README
dzenstatus.py
setup.py
DzenStatus.egg-info/PKG-INFO
DzenStatus.egg-info/SOURCES.txt
DzenStatus.egg-info/dependency_links.txt
DzenStatus.egg-info/entry_points.txt
DzenStatus.egg-info/top_level.txt