Metadata-Version: 1.0
Name: DzenStatus
Version: 0.1.4
Summary: A flexible (pkg_resources) plugin-based script for creating dzen2 status bars.
Home-page: http://bitbucket.org/enimihil/dzenstatus
Author: Greg S.
Author-email: enimihil@gmail.com
License: GPL
Keywords: status dzen dzen2 statusbar
Platform: UNKNOWN
Classifier: Development Status :: 3 - Alpha
Classifier: Environment :: X11 Applications
Classifier: Intended Audience :: End Users/Desktop
Classifier: License :: OSI Approved :: GNU General Public License (GPL)
Classifier: Natural Language :: English
Classifier: Operating System :: POSIX :: Linux
Classifier: Topic :: Desktop Environment
Classifier: Topic :: System :: Monitoring
Classifier: Topic :: Utilities
